{
    "example_source": [
        "▁我还",
        "澄清",
        "了",
        "在该",
        "会议上",
        "提出的",
        "若干",
        "事项",
        "。"
    ],
    "example_target": [
        "<s>",
        "▁i",
        "▁was",
        "▁able",
        "▁to",
        "▁provide",
        "▁clarification",
        "▁on",
        "▁some",
        "▁of",
        "▁the",
        "▁matters",
        "▁which",
        "▁were",
        "▁raised",
        "▁at",
        "▁that",
        "▁meeting",
        ".",
        "</s>"
    ],
    "hypotheses": [
        {
            "hypothesis": [
                "▁i",
                "▁should",
                "▁also",
                "▁like",
                "▁to",
                "▁clarify",
                "▁a",
                "▁number",
                "▁of",
                "▁matters",
                "▁at",
                "▁the",
                "▁meeting",
                "."
            ],
            "score": -12.623701095581055
        },
        {
            "hypothesis": [
                "▁i",
                "▁should",
                "▁also",
                "▁like",
                "▁to",
                "▁clarify",
                "▁a",
                "▁number",
                "▁of",
                "▁matters",
                "▁in",
                "▁the",
                "▁conference",
                "."
            ],
            "score": -13.03531551361084
        },
        {
            "hypothesis": [
                "▁i",
                "▁should",
                "▁also",
                "▁like",
                "▁to",
                "▁clarify",
                "▁a",
                "▁number",
                "▁of",
                "▁matters",
                "▁at",
                "▁the",
                "▁session",
                "."
            ],
            "score": -13.308161735534668
        },
        {
            "hypothesis": [
                "▁i",
                "▁should",
                "▁also",
                "▁like",
                "▁to",
                "▁clarify",
                "▁a",
                "▁number",
                "▁of",
                "▁matters",
                "▁at",
                "▁the",
                "▁meeting",
                "▁of",
                "▁the",
                "▁meeting",
                "."
            ],
            "score": -14.667020797729492
        },
        {
            "hypothesis": [
                "▁i",
                "▁should",
                "▁also",
                "▁like",
                "▁to",
                "▁clarify",
                "▁a",
                "▁number",
                "▁of",
                "▁matters",
                "▁at",
                "▁the",
                "▁meeting",
                "▁of",
                "▁the",
                "▁conference",
                "."
            ],
            "score": -14.829070091247559
        },
        {
            "hypothesis": [
                "▁i",
                "▁should",
                "▁also",
                "▁like",
                "▁to",
                "▁clarify",
                "▁a",
                "▁number",
                "▁of",
                "▁matters",
                "▁made",
                "▁by",
                "▁a",
                "▁number",
                "▁of",
                "▁matters",
                "."
            ],
            "score": -15.46035385131836
        },
        {
            "hypothesis": [
                "▁i",
                "▁should",
                "▁also",
                "▁like",
                "▁to",
                "▁clarify",
                "▁a",
                "▁number",
                "▁of",
                "▁matters",
                "▁made",
                "▁by",
                "▁a",
                "▁number",
                "▁of",
                "▁matters",
                "▁in",
                "▁the",
                "▁conference",
                "."
            ],
            "score": -17.12429428100586
        },
        {
            "hypothesis": [
                "▁i",
                "▁should",
                "▁also",
                "▁like",
                "▁to",
                "▁clarify",
                "▁a",
                "▁number",
                "▁of",
                "▁matters",
                "▁made",
                "▁by",
                "▁a",
                "▁number",
                "▁of",
                "▁matters",
                "▁made",
                "▁by",
                "▁the",
                "▁meeting",
                "."
            ],
            "score": -19.496295928955078
        },
        {
            "hypothesis": [
                "▁i",
                "▁should",
                "▁also",
                "▁like",
                "▁to",
                "▁clarify",
                "▁a",
                "▁number",
                "▁of",
                "▁matters",
                "▁made",
                "▁by",
                "▁a",
                "▁number",
                "▁of",
                "▁matters",
                "▁made",
                "▁by",
                "▁the",
                "▁secretariat",
                "."
            ],
            "score": -19.571533203125
        },
        {
            "hypothesis": [
                "▁i",
                "▁should",
                "▁also",
                "▁like",
                "▁to",
                "▁clarify",
                "▁a",
                "▁number",
                "▁of",
                "▁matters",
                "▁made",
                "▁by",
                "▁a",
                "▁number",
                "▁of",
                "▁matters",
                "▁which",
                "▁were",
                "▁made",
                "▁in",
                "▁the",
                "▁conference",
                "."
            ],
            "score": -20.71394157409668
        }
    ],
    "diagnostic_info": "eyJ0IjogIjIwMjUtMTAtMDZUMDU6Mzg6MTEuNTEyNTQ2IiwgImgiOiAiZ2FuZWV2LVByZWRhdG9yLVBIMzE1LTU1IiwgInUiOiAiZ2FuZWV2In0="
}